chroma_migrate/__init__.py
chroma_migrate/__main__.py
chroma_migrate/cli.py
chroma_migrate/import_chromadb.py
chroma_migrate/import_clickhouse.py
chroma_migrate/import_duckdb.py
chroma_migrate/utils.py
chroma_migrate-0.0.7.dist-info/LICENSE
chroma_migrate-0.0.7.dist-info/METADATA
chroma_migrate-0.0.7.dist-info/WHEEL
chroma_migrate-0.0.7.dist-info/entry_points.txt
chroma_migrate-0.0.7.dist-info/top_level.txt
chroma_migrate-0.0.7.dist-info/RECORD
