Metadata-Version: 2.1
Name: chroma_migrate
Version: 0.0.7
Summary: A tool for migrating to chroma versions >= 0.4.0
Author-email: Jeff Huber <jeff@trychroma.com>, Hammad Bashir <hammad@trychroma.com>
Keywords: chroma,migrate
Classifier: Programming Language :: Python :: 3
Classifier: License :: OSI Approved :: Apache Software License
Classifier: Operating System :: OS Independent
Requires-Python: >=3.7
License-File: LICENSE
